Tests/Standard/new/FSM/FSM_16State/src/FSM.v
module FSM_16state (
    input clk,
    input reset,
    input trigger,
    output reg [3:0] output_state
);

    parameter S0 = 16'b0000_0000_0000_0001,
              S1 = 16'b0000_0000_0000_0010,
              S2 = 16'b0000_0000_0000_0100,
              S3 = 16'b0000_0000_0000_1000,
              S4 = 16'b0000_0000_0001_0000,
              S5 = 16'b0000_0000_0010_0000,
              S6 = 16'b0000_0000_0100_0000,
              S7 = 16'b0000_0000_1000_0000,
              S8 = 16'b0000_0001_0000_0000,
              S9 = 16'b0000_0010_0000_0000,
              S10= 16'b0000_0100_0000_0000,
              S11= 16'b0000_1000_0000_0000,
              S12= 16'b0001_0000_0000_0000,
              S13= 16'b0010_0000_0000_0000,
              S14= 16'b0100_0000_0000_0000,
              S15= 16'b1000_0000_0000_0000;

    reg [15:0] state, next_state;

    always_ff @(posedge clk) begin
        if (reset == 1'b1) begin
            state <= S0;
        end
        else begin
            state <= next_state;
        end
    end

    always_comb begin 
        case (state)
            S0: begin
                output_state = 4'b0000;
                next_state = trigger ? S1 : S0;
            end
            S1: begin
                output_state = 4'b0001;
                next_state = trigger ? S2 : S0;
            end
            S2: begin
                output_state = 4'b0010;
                next_state = trigger ? S3 : S0;
            end
            S3: begin
                output_state = 4'b0011;
                next_state = trigger ? S4 : S0;
            end
            S4: begin
                output_state = 4'b0100;
                next_state = trigger ? S5 : S0;
            end
            S5: begin
                output_state = 4'b0101;
                next_state = trigger ? S6 : S0;
            end
            S6: begin
                output_state = 4'b0110;
                next_state = trigger ? S7 : S0;
            end
            S7: begin
                output_state = 4'b0111;
                next_state = trigger ? S8 : S0;
            end
            S8: begin
                output_state = 4'b1000;
                next_state = trigger ? S9 : S0;
            end
            S9: begin
                output_state = 4'b1001;
                next_state = trigger ? S10 : S0;
            end
            S10: begin
                output_state = 4'b1010;
                next_state = trigger ? S11 : S0;
            end
            S11: begin
                output_state = 4'b1011;
                next_state = trigger ? S12 : S0;
            end
            S12: begin
                output_state = 4'b1100;
                next_state = trigger ? S13 : S0;
            end
            S13: begin
                output_state = 4'b1101;
                next_state = trigger ? S14 : S0;
            end
            S14: begin
                output_state = 4'b1110;
                next_state = trigger ? S15 : S0;
            end
            S15: begin
                output_state = 4'b1111;
                next_state = trigger ? S0 : S15;
            end
            default: begin
                output_state = 4'b0000;
                next_state = S0;
            end
        endcase
    end
endmodule

Tests/Challenging/final/FSM/src/FSM_tb.v
module FSM_16state_tb;

reg clk;
reg reset;
reg trigger;
wire [3:0] output_state;

parameter CLK_T            = 10000;

parameter   S0 = 16'b0000_0000_0000_0001,
            S1 = 16'b0000_0000_0000_0010,
            S2 = 16'b0000_0000_0000_0100,
            S3 = 16'b0000_0000_0000_1000,
            S4 = 16'b0000_0000_0001_0000,
            S5 = 16'b0000_0000_0010_0000,
            S6 = 16'b0000_0000_0100_0000,
            S7 = 16'b0000_0000_1000_0000,
            S8 = 16'b0000_0001_0000_0000,
            S9 = 16'b0000_0010_0000_0000,
            S10= 16'b0000_0100_0000_0000,
            S11= 16'b0000_1000_0000_0000,
            S12= 16'b0001_0000_0000_0000,
            S13= 16'b0010_0000_0000_0000,
            S14= 16'b0100_0000_0000_0000,
            S15= 16'b1000_0000_0000_0000;

initial clk = 1'b0;
always #(CLK_T / 2) clk = ~clk;

FSM_16state #(
    .S0(S0),
    .S1(S1),
    .S2(S2),
    .S3(S3),
    .S4(S4),
    .S5(S5),
    .S6(S6),
    .S7(S7),
    .S8(S8),
    .S9(S9),
    .S10(S10),
    .S11(S11),
    .S12(S12),
    .S13(S13),
    .S14(S14),
    .S15(S15)
) DUT (
    .clk(clk),
    .reset(reset),
    .trigger(trigger),
    .output_state(output_state)
);

task apply_reset;
  begin
    @(posedge clk);
    reset = 1'b1;
    @(posedge clk);
    reset = 1'b0;
  end
endtask

initial begin
  $dumpfile("FSM.vcd");
  $dumpvars(0, FSM_16state);
end

initial begin
    reset = 1'b0;
    trigger = 1'b0;
    apply_reset;

    repeat(10) @(posedge clk);
    trigger <= 1'b1;
    @(posedge clk);
    trigger <= 1'b1;
    
    repeat(100) @(posedge clk);
    $stop;
end
endmodule

Tests/Challenging/final/FSM/sim/FSM.vcd
$date
   Fri Mar 20 14:20:55 2026
$end

$version
  2024.2.0
  $dumpfile ("FSM.vcd") 
$end

$timescale
  1ps
$end

$scope module FSM_16state_tb $end
$var reg 1 ! clk $end
$var reg 1 " reset $end
$var reg 1 # trigger $end
$var wire 4 $ output_state [3:0] $end
$scope module DUT $end
$var wire 1 % clk $end
$var wire 1 & reset $end
$var wire 1 ' trigger $end
$var reg 4 ( output_state [3:0] $end
$var reg 16 ) state [15:0] $end
$var reg 16 * next_state [15:0] $end
$upscope $end
$scope task apply_reset $end
$upscope $end
$upscope $end
$enddefinitions $end

#0
$dumpvars
0!
0"
0#
b0 $
0%
0&
0'
b0 (
bx )
b1 *
$end

#5000000
1!
1"
1%
1&
b1 )

#10000000
0!
0%

#15000000
1!
0"
1%
0&

#20000000
0!
0%

#25000000
1!
1%

#30000000
0!
0%

#35000000
1!
1%

#40000000
0!
0%

#45000000
1!
1%

#50000000
0!
0%

#55000000
1!
1%

#60000000
0!
0%

#65000000
1!
1%

#70000000
0!
0%

#75000000
1!
1%

#80000000
0!
0%

#85000000
1!
1%

#90000000
0!
0%

#95000000
1!
1%

#100000000
0!
0%

#105000000
1!
1%

#110000000
0!
0%

#115000000
1!
1#
1%
1'
b10 *

#120000000
0!
0%

#125000000
1!
b1 $
1%
b1 (
b10 )
b100 *

#130000000
0!
0%

#135000000
1!
b10 $
1%
b10 (
b100 )
b1000 *

#140000000
0!
0%

#145000000
1!
b11 $
1%
b11 (
b1000 )
b10000 *

#150000000
0!
0%

#155000000
1!
b100 $
1%
b100 (
b10000 )
b100000 *

#160000000
0!
0%

#165000000
1!
b101 $
1%
b101 (
b100000 )
b1000000 *

#170000000
0!
0%

#175000000
1!
b110 $
1%
b110 (
b1000000 )
b10000000 *

#180000000
0!
0%

#185000000
1!
b111 $
1%
b111 (
b10000000 )
b100000000 *

#190000000
0!
0%

#195000000
1!
b1000 $
1%
b1000 (
b100000000 )
b1000000000 *

#200000000
0!
0%

#205000000
1!
b1001 $
1%
b1001 (
b1000000000 )
b10000000000 *

#210000000
0!
0%

#215000000
1!
b1010 $
1%
b1010 (
b10000000000 )
b100000000000 *

#220000000
0!
0%

#225000000
1!
b1011 $
1%
b1011 (
b100000000000 )
b1000000000000 *

#230000000
0!
0%

#235000000
1!
b1100 $
1%
b1100 (
b1000000000000 )
b10000000000000 *

#240000000
0!
0%

#245000000
1!
b1101 $
1%
b1101 (
b10000000000000 )
b100000000000000 *

#250000000
0!
0%

#255000000
1!
b1110 $
1%
b1110 (
b100000000000000 )
b1000000000000000 *

#260000000
0!
0%

#265000000
1!
b1111 $
1%
b1111 (
b1000000000000000 )
b1 *

#270000000
0!
0%

#275000000
1!
b0 $
1%
b0 (
b1 )
b10 *

#280000000
0!
0%

#285000000
1!
b1 $
1%
b1 (
b10 )
b100 *

#290000000
0!
0%

#295000000
1!
b10 $
1%
b10 (
b100 )
b1000 *

#300000000
0!
0%

#305000000
1!
b11 $
1%
b11 (
b1000 )
b10000 *

#310000000
0!
0%

#315000000
1!
b100 $
1%
b100 (
b10000 )
b100000 *

#320000000
0!
0%

#325000000
1!
b101 $
1%
b101 (
b100000 )
b1000000 *

#330000000
0!
0%

#335000000
1!
b110 $
1%
b110 (
b1000000 )
b10000000 *

#340000000
0!
0%

#345000000
1!
b111 $
1%
b111 (
b10000000 )
b100000000 *

#350000000
0!
0%

#355000000
1!
b1000 $
1%
b1000 (
b100000000 )
b1000000000 *

#360000000
0!
0%

#365000000
1!
b1001 $
1%
b1001 (
b1000000000 )
b10000000000 *

#370000000
0!
0%

#375000000
1!
b1010 $
1%
b1010 (
b10000000000 )
b100000000000 *

#380000000
0!
0%

#385000000
1!
b1011 $
1%
b1011 (
b100000000000 )
b1000000000000 *

#390000000
0!
0%

#395000000
1!
b1100 $
1%
b1100 (
b1000000000000 )
b10000000000000 *

#400000000
0!
0%

#405000000
1!
b1101 $
1%
b1101 (
b10000000000000 )
b100000000000000 *

#410000000
0!
0%

#415000000
1!
b1110 $
1%
b1110 (
b100000000000000 )
b1000000000000000 *

#420000000
0!
0%

#425000000
1!
b1111 $
1%
b1111 (
b1000000000000000 )
b1 *

#430000000
0!
0%

#435000000
1!
b0 $
1%
b0 (
b1 )
b10 *

#440000000
0!
0%

#445000000
1!
b1 $
1%
b1 (
b10 )
b100 *

#450000000
0!
0%

#455000000
1!
b10 $
1%
b10 (
b100 )
b1000 *

#460000000
0!
0%

#465000000
1!
b11 $
1%
b11 (
b1000 )
b10000 *

#470000000
0!
0%

#475000000
1!
b100 $
1%
b100 (
b10000 )
b100000 *

#480000000
0!
0%

#485000000
1!
b101 $
1%
b101 (
b100000 )
b1000000 *

#490000000
0!
0%

#495000000
1!
b110 $
1%
b110 (
b1000000 )
b10000000 *

#500000000
0!
0%

#505000000
1!
b111 $
1%
b111 (
b10000000 )
b100000000 *

#510000000
0!
0%

#515000000
1!
b1000 $
1%
b1000 (
b100000000 )
b1000000000 *

#520000000
0!
0%

#525000000
1!
b1001 $
1%
b1001 (
b1000000000 )
b10000000000 *

#530000000
0!
0%

#535000000
1!
b1010 $
1%
b1010 (
b10000000000 )
b100000000000 *

#540000000
0!
0%

#545000000
1!
b1011 $
1%
b1011 (
b100000000000 )
b1000000000000 *

#550000000
0!
0%

#555000000
1!
b1100 $
1%
b1100 (
b1000000000000 )
b10000000000000 *

#560000000
0!
0%

#565000000
1!
b1101 $
1%
b1101 (
b10000000000000 )
b100000000000000 *

#570000000
0!
0%

#575000000
1!
b1110 $
1%
b1110 (
b100000000000000 )
b1000000000000000 *

#580000000
0!
0%

#585000000
1!
b1111 $
1%
b1111 (
b1000000000000000 )
b1 *

#590000000
0!
0%

#595000000
1!
b0 $
1%
b0 (
b1 )
b10 *

#600000000
0!
0%

#605000000
1!
b1 $
1%
b1 (
b10 )
b100 *

#610000000
0!
0%

#615000000
1!
b10 $
1%
b10 (
b100 )
b1000 *

#620000000
0!
0%

#625000000
1!
b11 $
1%
b11 (
b1000 )
b10000 *

#630000000
0!
0%

#635000000
1!
b100 $
1%
b100 (
b10000 )
b100000 *

#640000000
0!
0%

#645000000
1!
b101 $
1%
b101 (
b100000 )
b1000000 *

#650000000
0!
0%

#655000000
1!
b110 $
1%
b110 (
b1000000 )
b10000000 *

#660000000
0!
0%

#665000000
1!
b111 $
1%
b111 (
b10000000 )
b100000000 *

#670000000
0!
0%

#675000000
1!
b1000 $
1%
b1000 (
b100000000 )
b1000000000 *

#680000000
0!
0%

#685000000
1!
b1001 $
1%
b1001 (
b1000000000 )
b10000000000 *

#690000000
0!
0%

#695000000
1!
b1010 $
1%
b1010 (
b10000000000 )
b100000000000 *

#700000000
0!
0%

#705000000
1!
b1011 $
1%
b1011 (
b100000000000 )
b1000000000000 *

#710000000
0!
0%

#715000000
1!
b1100 $
1%
b1100 (
b1000000000000 )
b10000000000000 *

#720000000
0!
0%

#725000000
1!
b1101 $
1%
b1101 (
b10000000000000 )
b100000000000000 *

#730000000
0!
0%

#735000000
1!
b1110 $
1%
b1110 (
b100000000000000 )
b1000000000000000 *

#740000000
0!
0%

#745000000
1!
b1111 $
1%
b1111 (
b1000000000000000 )
b1 *

#750000000
0!
0%

#755000000
1!
b0 $
1%
b0 (
b1 )
b10 *

#760000000
0!
0%

#765000000
1!
b1 $
1%
b1 (
b10 )
b100 *

#770000000
0!
0%

#775000000
1!
b10 $
1%
b10 (
b100 )
b1000 *

#780000000
0!
0%

#785000000
1!
b11 $
1%
b11 (
b1000 )
b10000 *

#790000000
0!
0%

#795000000
1!
b100 $
1%
b100 (
b10000 )
b100000 *

#800000000
0!
0%

#805000000
1!
b101 $
1%
b101 (
b100000 )
b1000000 *

#810000000
0!
0%

#815000000
1!
b110 $
1%
b110 (
b1000000 )
b10000000 *

#820000000
0!
0%

#825000000
1!
b111 $
1%
b111 (
b10000000 )
b100000000 *

#830000000
0!
0%

#835000000
1!
b1000 $
1%
b1000 (
b100000000 )
b1000000000 *

#840000000
0!
0%

#845000000
1!
b1001 $
1%
b1001 (
b1000000000 )
b10000000000 *

#850000000
0!
0%

#855000000
1!
b1010 $
1%
b1010 (
b10000000000 )
b100000000000 *

#860000000
0!
0%

#865000000
1!
b1011 $
1%
b1011 (
b100000000000 )
b1000000000000 *

#870000000
0!
0%

#875000000
1!
b1100 $
1%
b1100 (
b1000000000000 )
b10000000000000 *

#880000000
0!
0%

#885000000
1!
b1101 $
1%
b1101 (
b10000000000000 )
b100000000000000 *

#890000000
0!
0%

#895000000
1!
b1110 $
1%
b1110 (
b100000000000000 )
b1000000000000000 *

#900000000
0!
0%

#905000000
1!
b1111 $
1%
b1111 (
b1000000000000000 )
b1 *

#910000000
0!
0%

#915000000
1!
b0 $
1%
b0 (
b1 )
b10 *

#920000000
0!
0%

#925000000
1!
b1 $
1%
b1 (
b10 )
b100 *

#930000000
0!
0%

#935000000
1!
b10 $
1%
b10 (
b100 )
b1000 *

#940000000
0!
0%

#945000000
1!
b11 $
1%
b11 (
b1000 )
b10000 *

#950000000
0!
0%

#955000000
1!
b100 $
1%
b100 (
b10000 )
b100000 *

#960000000
0!
0%

#965000000
1!
b101 $
1%
b101 (
b100000 )
b1000000 *

#970000000
0!
0%

#975000000
1!
b110 $
1%
b110 (
b1000000 )
b10000000 *

#980000000
0!
0%

#985000000
1!
b111 $
1%
b111 (
b10000000 )
b100000000 *

#990000000
0!
0%

#995000000
1!
b1000 $
1%
b1000 (
b100000000 )
b1000000000 *

#1000000000
0!
0%

#1005000000
1!
b1001 $
1%
b1001 (
b1000000000 )
b10000000000 *

#1010000000
0!
0%

#1015000000
1!
b1010 $
1%
b1010 (
b10000000000 )
b100000000000 *

#1020000000
0!
0%

#1025000000
1!
b1011 $
1%
b1011 (
b100000000000 )
b1000000000000 *

#1030000000
0!
0%

#1035000000
1!
b1100 $
1%
b1100 (
b1000000000000 )
b10000000000000 *

#1040000000
0!
0%

#1045000000
1!
b1101 $
1%
b1101 (
b10000000000000 )
b100000000000000 *

#1050000000
0!
0%

#1055000000
1!
b1110 $
1%
b1110 (
b100000000000000 )
b1000000000000000 *

#1060000000
0!
0%

#1065000000
1!
b1111 $
1%
b1111 (
b1000000000000000 )
b1 *

#1070000000
0!
0%

#1075000000
1!
b0 $
1%
b0 (
b1 )
b10 *

#1080000000
0!
0%

#1085000000
1!
b1 $
1%
b1 (
b10 )
b100 *

#1090000000
0!
0%

#1095000000
1!
b10 $
1%
b10 (
b100 )
b1000 *

#1100000000
0!
0%

#1105000000
1!
b11 $
1%
b11 (
b1000 )
b10000 *

#1110000000
0!
0%

#1115000000
1!
b100 $
1%
b100 (
b10000 )
b100000 *

